{"name":"Enterprise Monitoring System","tagline":"","body":"# EMS - Enterprise Monitoring System\r\n\r\n## Java Web Application - SCADA / HMI server\r\n\r\n### Overview\r\nIn systems engineering, a system monitor (SM) is a process within a distributed system for collecting and storing state data. **Network monitoring** or more simply monitoring is the use of a system that constantly monitors a computer or a device for slow or failing components and that notifies the administrator. The **Internet of Things (IoT)** refers to the interconnection of uniquely identifiable embedded computing-like devices within the existing Internet infrastructure. \r\n\r\n### Project scope\r\nProject scope is creating an application that can monitor remote devices with different protocols. Application offers easly customizable dashboard, a pluggable and extensible data model, advanced configuration functionalities.\r\n\r\n### Technology\r\n * Java\r\n * Spring (Core, Security, Data)\r\n * Restful Web Services\r\n * Javascript & HTML5\r\n * JSON & JSON Schema\r\n * MongoDB\r\n\r\n### Status & Notes\r\nProject is still in its early stages.\r\n\r\n### Demo\r\nPlanned...\r\n","google":"UA-202273-2","note":"Don't delete this file! It's used internally to help with page regeneration."}